{"no": 22, "name": "灰飞虱", "info": "灰飞虱Laodelphax striatellus Fallén属同翅目，飞虱科。分布在中国各省，长江中下游及华北发生多。为害茭白、水稻、小麦、大麦、玉米、高粱、甘蔗、稗草等。", "danger": "成、若虫吸食茭白等寄主汁液，引起黄叶或枯死。", "morph": "(1)成虫。成虫长翅型体长(连翅)4～5cm，短翅型体长2.4～2.6cm，具翅斑。雄虫体黑褐色，雌虫淡黄色，头顶稍突出，额黑褐色。中胸背板雄虫为黑褐色，仅后缘淡黄色，雌虫则中部淡黄色，两侧色较深。(2)卵。卵长椭圆形，稍弯曲。卵帽外露，在产卵痕内排列成念球状，卵条内卵粒成簇或双行排列。卵粒初产时为乳白色，半透明，孵化前出现紫红色眼点。(3)若虫。灰褐色，腹部背面两则色稍深，中央色浅淡。", "gen": "(1)发生世代。湖北、四川、江苏、浙江、上海每年发生5～6代，福建7～8代，北方4～5代。(2)越冬。在福建、两广、云南冬季3种虫态可见，其他地区多以3、4龄若虫在麦田、绿肥田等处禾本科杂草上越冬。(3)发生时期。早春均温高于10℃越冬若虫羽化。发育适温15～28℃，冬暖夏凉易发生。", "habit": "(1)成虫。成虫有明显趋嫩绿、茂密习性，长翅型成虫有趋光性。成虫产卵多在下午，卵产于叶鞘及叶片基部的中脉两侧。(2)幼虫。越冬若虫3月出蛰取食麦苗和杂草，羽化后多为短翅型成虫，繁殖1代后产生长翅型成虫，迁移至棉田为害。", "measure": "若虫盛发时喷洒10%吡虫啉可湿性粉剂 1 500倍液，或每公顷用药量为225g。"}